dumbquotes/__init__.py
dumbquotes/_nbdev.py
dumbquotes/core.py
dumbquotes-0.0.3.dist-info/LICENSE
dumbquotes-0.0.3.dist-info/METADATA
dumbquotes-0.0.3.dist-info/WHEEL
dumbquotes-0.0.3.dist-info/top_level.txt
dumbquotes-0.0.3.dist-info/RECORD
